LICENSE
README.md
setup.py
KeyboardManager/__init__.py
KeyboardManager/listenKeyboard.py
hoyl_keyboard_manager.egg-info/PKG-INFO
hoyl_keyboard_manager.egg-info/SOURCES.txt
hoyl_keyboard_manager.egg-info/dependency_links.txt
hoyl_keyboard_manager.egg-info/requires.txt
hoyl_keyboard_manager.egg-info/top_level.txt