Metadata-Version: 2.1
Name: hoyl-keyboard-manager
Version: 1.0.1
Summary: Pequena biblioteca para consultar eventos do teclado
Author: Alan Reis Anjos
Author-email: alanreisanjo@gmail.com
License: MIT License
Keywords: Hoyl Keyboard Manager
License-File: LICENSE
Requires-Dist: keyboard
